<?xml version="1.0" encoding="UTF-8"?>
<objects serializationModel="Studio.01.07.00">
    <object class="AudioFile" id="{5d9c9944-1346-4675-8488-6994d6633029}">
        <property name="frequencyInKHz">
            <value>44.0999985</value>
        </property>
        <property name="channelCount">
            <value>2</value>
        </property>
        <property name="length">
            <value>3.3649659863945578</value>
        </property>
        <property name="audioFilePath">
            <value>$(AUDIO_BIN_DIR)/On Board July 24 {db428f0e-db00-405c-a45f-0948d8fb7baa}.wav</value>
        </property>
        <relationship name="container">
            <destination>{47d2c2e4-ae90-4a7a-b9eb-1d723b7f342d}</destination>
        </relationship>
    </object>
</objects>
