<?xml version="1.0" encoding="UTF-8"?>
<objects serializationModel="Studio.01.07.00">
    <object class="AudioFile" id="{889e2d03-dd32-4e16-a677-c5d77d9f662a}">
        <property name="frequencyInKHz">
            <value>44.0999985</value>
        </property>
        <property name="channelCount">
            <value>2</value>
        </property>
        <property name="length">
            <value>0.25074829931972792</value>
        </property>
        <property name="audioFilePath">
            <value>$(AUDIO_BIN_DIR)/foot2pedal2 {96e6e8ee-3e84-4e65-9b1f-33df0e78e453}.wav</value>
        </property>
        <relationship name="container">
            <destination>{47d2c2e4-ae90-4a7a-b9eb-1d723b7f342d}</destination>
        </relationship>
    </object>
</objects>
